<?xml version="1.0" encoding="UTF-8" ?>
<!DOCTYPE mapper PUBLIC "-//mybatis.org//DTD Mapper 3.0//EN" "http://mybatis.org/dtd/mybatis-3-mapper.dtd" >
<mapper namespace="com.mall.dao.CmsHelpCategoryMapper" >
  <resultMap id="BaseResultMap" type="com.mall.pojo.CmsHelpCategory" >
    <!--
      WARNING - @mbggenerated
      This element is automatically generated by MyBatis Generator, do not modify.
    -->
    <id column="id" property="id" jdbcType="BIGINT" />
    <result column="name" property="name" jdbcType="VARCHAR" />
    <result column="icon" property="icon" jdbcType="VARCHAR" />
    <result column="help_count" property="helpCount" jdbcType="INTEGER" />
    <result column="show_status" property="showStatus" jdbcType="INTEGER" />
    <result column="sort" property="sort" jdbcType="INTEGER" />
  </resultMap>
  <delete id="deleteByPrimaryKey" parameterType="java.lang.Long" >
    <!--
      WARNING - @mbggenerated
      This element is automatically generated by MyBatis Generator, do not modify.
    -->
    delete from cms_help_category
    where id = #{id,jdbcType=BIGINT}
  </delete>
  <insert id="insert" parameterType="com.mall.pojo.CmsHelpCategory" >
    <!--
      WARNING - @mbggenerated
      This element is automatically generated by MyBatis Generator, do not modify.
    -->
    insert into cms_help_category (id, `name`, icon, 
      help_count, show_status, sort
      )
    values (#{id,jdbcType=BIGINT}, #{name,jdbcType=VARCHAR}, #{icon,jdbcType=VARCHAR}, 
      #{helpCount,jdbcType=INTEGER}, #{showStatus,jdbcType=INTEGER}, #{sort,jdbcType=INTEGER}
      )
  </insert>
  <update id="updateByPrimaryKey" parameterType="com.mall.pojo.CmsHelpCategory" >
    <!--
      WARNING - @mbggenerated
      This element is automatically generated by MyBatis Generator, do not modify.
    -->
    update cms_help_category
    set `name` = #{name,jdbcType=VARCHAR},
      icon = #{icon,jdbcType=VARCHAR},
      help_count = #{helpCount,jdbcType=INTEGER},
      show_status = #{showStatus,jdbcType=INTEGER},
      sort = #{sort,jdbcType=INTEGER}
    where id = #{id,jdbcType=BIGINT}
  </update>
  <select id="selectByPrimaryKey" resultMap="BaseResultMap" parameterType="java.lang.Long" >
    <!--
      WARNING - @mbggenerated
      This element is automatically generated by MyBatis Generator, do not modify.
    -->
    select id, `name`, icon, help_count, show_status, sort
    from cms_help_category
    where id = #{id,jdbcType=BIGINT}
  </select>
  <select id="selectAll" resultMap="BaseResultMap" >
    <!--
      WARNING - @mbggenerated
      This element is automatically generated by MyBatis Generator, do not modify.
    -->
    select id, `name`, icon, help_count, show_status, sort
    from cms_help_category
  </select>
</mapper>